{
  "__schema": {
    "queryType": {
      "name": "Query"
    },
    "mutationType": {
      "name": "Mutation"
    },
    "subscriptionType": null,
    "types": [
      {
        "kind": "OBJECT",
        "name": "Query",
        "description": null,
        "fields": [
          {
            "name": "getUserUsingApp",
            "description": null,
            "args": [
              {
                "name": "userData",
                "description": null,
                "type": {
                  "kind": "LIST",
                  "name": null,
                  "ofType": {
                    "kind": "SCALAR",
                    "name": "String",
                    "ofType": null
                  }
                },
                "defaultValue": null
              },
              {
                "name": "userId",
                "description": null,
                "type": {
                  "kind": "SCALAR",
                  "name": "ID",
                  "ofType": null
                },
                "defaultValue": null
              },
              {
                "name": "threadId",
                "description": null,
                "type": {
                  "kind": "SCALAR",
                  "name": "ID",
                  "ofType": null
                },
                "defaultValue": null
              }
            ],
            "type": {
              "kind": "OBJECT",
              "name": "UserDataResponse",
              "ofType": null
            },
            "isDeprecated": false,
            "deprecationReason": null
          },
          {
            "name": "getAllUsers",
            "description": null,
            "args": [],
            "type": {
              "kind": "OBJECT",
              "name": "User",
              "ofType": null
            },
            "isDeprecated": false,
            "deprecationReason": null
          },
          {
            "name": "getOperator",
            "description": null,
            "args": [
              {
                "name": "operatorId",
                "description": null,
                "type": {
                  "kind": "SCALAR",
                  "name": "ID",
                  "ofType": null
                },
                "defaultValue": null
              }
            ],
            "type": {
              "kind": "OBJECT",
              "name": "Operator",
              "ofType": null
            },
            "isDeprecated": false,
            "deprecationReason": null
          },
          {
            "name": "getApnDetails",
            "description": null,
            "args": [
              {
                "name": "operatorId",
                "description": null,
                "type": {
                  "kind": "SCALAR",
                  "name": "ID",
                  "ofType": null
                },
                "defaultValue": null
              }
            ],
            "type": {
              "kind": "OBJECT",
              "name": "APN",
              "ofType": null
            },
            "isDeprecated": false,
            "deprecationReason": null
          },
          {
            "name": "getAppConfig",
            "description": null,
            "args": [
              {
                "name": "operatorId",
                "description": null,
                "type": {
                  "kind": "SCALAR",
                  "name": "ID",
                  "ofType": null
                },
                "defaultValue": null
              }
            ],
            "type": {
              "kind": "OBJECT",
              "name": "AppConfigRes",
              "ofType": null
            },
            "isDeprecated": false,
            "deprecationReason": null
          },
          {
            "name": "getThread",
            "description": null,
            "args": [
              {
                "name": "threadId",
                "description": null,
                "type": {
                  "kind": "SCALAR",
                  "name": "ID",
                  "ofType": null
                },
                "defaultValue": null
              }
            ],
            "type": {
              "kind": "OBJECT",
              "name": "Thread",
              "ofType": null
            },
            "isDeprecated": false,
            "deprecationReason": null
          },
          {
            "name": "getThreadList",
            "description": null,
            "args": [
              {
                "name": "userId",
                "description": null,
                "type": {
                  "kind": "SCALAR",
                  "name": "ID",
                  "ofType": null
                },
                "defaultValue": null
              }
            ],
            "type": {
              "kind": "OBJECT",
              "name": "ThreadListRes",
              "ofType": null
            },
            "isDeprecated": false,
            "deprecationReason": null
          },
          {
            "name": "getAttachment",
            "description": null,
            "args": [
              {
                "name": "attachmentId",
                "description": null,
                "type": {
                  "kind": "SCALAR",
                  "name": "ID",
                  "ofType": null
                },
                "defaultValue": null
              }
            ],
            "type": {
              "kind": "OBJECT",
              "name": "Attachment",
              "ofType": null
            },
            "isDeprecated": false,
            "deprecationReason": null
          },
          {
            "name": "getMessage",
            "description": null,
            "args": [
              {
                "name": "messageId",
                "description": null,
                "type": {
                  "kind": "SCALAR",
                  "name": "ID",
                  "ofType": null
                },
                "defaultValue": null
              }
            ],
            "type": {
              "kind": "OBJECT",
              "name": "Message",
              "ofType": null
            },
            "isDeprecated": false,
            "deprecationReason": null
          },
          {
            "name": "getMessageList",
            "description": null,
            "args": [
              {
                "name": "senderId",
                "description": null,
                "type": {
                  "kind": "SCALAR",
                  "name": "ID",
                  "ofType": null
                },
                "defaultValue": null
              },
              {
                "name": "receiverId",
                "description": null,
                "type": {
                  "kind": "SCALAR",
                  "name": "ID",
                  "ofType": null
                },
                "defaultValue": null
              },
              {
                "name": "threadId",
                "description": null,
                "type": {
                  "kind": "SCALAR",
                  "name": "ID",
                  "ofType": null
                },
                "defaultValue": null
              }
            ],
            "type": {
              "kind": "OBJECT",
              "name": "GetMessageListRes",
              "ofType": null
            },
            "isDeprecated": false,
            "deprecationReason": null
          },
          {
            "name": "getGroupMessageList",
            "description": null,
            "args": [
              {
                "name": "senderId",
                "description": null,
                "type": {
                  "kind": "SCALAR",
                  "name": "ID",
                  "ofType": null
                },
                "defaultValue": null
              },
              {
                "name": "threadId",
                "description": null,
                "type": {
                  "kind": "SCALAR",
                  "name": "ID",
                  "ofType": null
                },
                "defaultValue": null
              }
            ],
            "type": {
              "kind": "OBJECT",
              "name": "GetMessageListRes",
              "ofType": null
            },
            "isDeprecated": false,
            "deprecationReason": null
          }
        ],
        "inputFields": null,
        "interfaces": [],
        "enumValues": null,
        "possibleTypes": null
      },
      {
        "kind": "SCALAR",
        "name": "String",
        "description": "The `String` scalar type represents textual data, represented as UTF-8 character sequences. The String type is most often used by GraphQL to represent free-form human-readable text.",
        "fields": null,
        "inputFields": null,
        "interfaces": null,
        "enumValues": null,
        "possibleTypes": null
      },
      {
        "kind": "SCALAR",
        "name": "ID",
        "description": "The `ID` scalar type represents a unique identifier, often used to refetch an object or as key for a cache. The ID type appears in a JSON response as a String; however, it is not intended to be human-readable. When expected as an input type, any string (such as `\"4\"`) or integer (such as `4`) input value will be accepted as an ID.",
        "fields": null,
        "inputFields": null,
        "interfaces": null,
        "enumValues": null,
        "possibleTypes": null
      },
      {
        "kind": "OBJECT",
        "name": "UserDataResponse",
        "description": null,
        "fields": [
          {
            "name": "userData",
            "description": null,
            "args": [],
            "type": {
              "kind": "LIST",
              "name": null,
              "ofType": {
                "kind": "OBJECT",
                "name": "UserData",
                "ofType": null
              }
            },
            "isDeprecated": false,
            "deprecationReason": null
          }
        ],
        "inputFields": null,
        "interfaces": [],
        "enumValues": null,
        "possibleTypes": null
      },
      {
        "kind": "OBJECT",
        "name": "UserData",
        "description": null,
        "fields": [
          {
            "name": "name",
            "description": null,
            "args": [],
            "type": {
              "kind": "SCALAR",
              "name": "String",
              "ofType": null
            },
            "isDeprecated": false,
            "deprecationReason": null
          },
          {
            "name": "userId",
            "description": null,
            "args": [],
            "type": {
              "kind": "SCALAR",
              "name": "ID",
              "ofType": null
            },
            "isDeprecated": false,
            "deprecationReason": null
          },
          {
            "name": "msisdn",
            "description": null,
            "args": [],
            "type": {
              "kind": "SCALAR",
              "name": "String",
              "ofType": null
            },
            "isDeprecated": false,
            "deprecationReason": null
          },
          {
            "name": "operator",
            "description": null,
            "args": [],
            "type": {
              "kind": "SCALAR",
              "name": "String",
              "ofType": null
            },
            "isDeprecated": false,
            "deprecationReason": null
          },
          {
            "name": "createdAt",
            "description": null,
            "args": [],
            "type": {
              "kind": "SCALAR",
              "name": "Date",
              "ofType": null
            },
            "isDeprecated": false,
            "deprecationReason": null
          },
          {
            "name": "updatedAt",
            "description": null,
            "args": [],
            "type": {
              "kind": "SCALAR",
              "name": "Date",
              "ofType": null
            },
            "isDeprecated": false,
            "deprecationReason": null
          },
          {
            "name": "lastActive",
            "description": null,
            "args": [],
            "type": {
              "kind": "SCALAR",
              "name": "String",
              "ofType": null
            },
            "isDeprecated": false,
            "deprecationReason": null
          },
          {
            "name": "userStatus",
            "description": null,
            "args": [],
            "type": {
              "kind": "SCALAR",
              "name": "Int",
              "ofType": null
            },
            "isDeprecated": false,
            "deprecationReason": null
          },
          {
            "name": "chatFeature",
            "description": null,
            "args": [],
            "type": {
              "kind": "SCALAR",
              "name": "Int",
              "ofType": null
            },
            "isDeprecated": false,
            "deprecationReason": null
          },
          {
            "name": "message",
            "description": null,
            "args": [],
            "type": {
              "kind": "SCALAR",
              "name": "String",
              "ofType": null
            },
            "isDeprecated": false,
            "deprecationReason": null
          },
          {
            "name": "messageDate",
            "description": null,
            "args": [],
            "type": {
              "kind": "SCALAR",
              "name": "Date",
              "ofType": null
            },
            "isDeprecated": false,
            "deprecationReason": null
          },
          {
            "name": "threadId",
            "description": null,
            "args": [],
            "type": {
              "kind": "SCALAR",
              "name": "ID",
              "ofType": null
            },
            "isDeprecated": false,
            "deprecationReason": null
          },
          {
            "name": "isGroup",
            "description": null,
            "args": [],
            "type": {
              "kind": "SCALAR",
              "name": "Boolean",
              "ofType": null
            },
            "isDeprecated": false,
            "deprecationReason": null
          }
        ],
        "inputFields": null,
        "interfaces": [],
        "enumValues": null,
        "possibleTypes": null
      },
      {
        "kind": "SCALAR",
        "name": "Date",
        "description": null,
        "fields": null,
        "inputFields": null,
        "interfaces": null,
        "enumValues": null,
        "possibleTypes": null
      },
      {
        "kind": "SCALAR",
        "name": "Int",
        "description": "The `Int` scalar type represents non-fractional signed whole numeric values. Int can represent values between -(2^31) and 2^31 - 1.",
        "fields": null,
        "inputFields": null,
        "interfaces": null,
        "enumValues": null,
        "possibleTypes": null
      },
      {
        "kind": "SCALAR",
        "name": "Boolean",
        "description": "The `Boolean` scalar type represents `true` or `false`.",
        "fields": null,
        "inputFields": null,
        "interfaces": null,
        "enumValues": null,
        "possibleTypes": null
      },
      {
        "kind": "OBJECT",
        "name": "User",
        "description": null,
        "fields": [
          {
            "name": "_id",
            "description": null,
            "args": [],
            "type": {
              "kind": "SCALAR",
              "name": "ID",
              "ofType": null
            },
            "isDeprecated": false,
            "deprecationReason": null
          },
          {
            "name": "name",
            "description": null,
            "args": [],
            "type": {
              "kind": "SCALAR",
              "name": "String",
              "ofType": null
            },
            "isDeprecated": false,
            "deprecationReason": null
          },
          {
            "name": "msisdn",
            "description": null,
            "args": [],
            "type": {
              "kind": "SCALAR",
              "name": "String",
              "ofType": null
            },
            "isDeprecated": false,
            "deprecationReason": null
          },
          {
            "name": "operator",
            "description": null,
            "args": [],
            "type": {
              "kind": "SCALAR",
              "name": "String",
              "ofType": null
            },
            "isDeprecated": false,
            "deprecationReason": null
          }
        ],
        "inputFields": null,
        "interfaces": [],
        "enumValues": null,
        "possibleTypes": null
      },
      {
        "kind": "OBJECT",
        "name": "Operator",
        "description": null,
        "fields": [
          {
            "name": "_id",
            "description": null,
            "args": [],
            "type": {
              "kind": "SCALAR",
              "name": "ID",
              "ofType": null
            },
            "isDeprecated": false,
            "deprecationReason": null
          },
          {
            "name": "operatorId",
            "description": null,
            "args": [],
            "type": {
              "kind": "SCALAR",
              "name": "ID",
              "ofType": null
            },
            "isDeprecated": false,
            "deprecationReason": null
          },
          {
            "name": "name",
            "description": null,
            "args": [],
            "type": {
              "kind": "SCALAR",
              "name": "String",
              "ofType": null
            },
            "isDeprecated": false,
            "deprecationReason": null
          }
        ],
        "inputFields": null,
        "interfaces": [],
        "enumValues": null,
        "possibleTypes": null
      },
      {
        "kind": "OBJECT",
        "name": "APN",
        "description": null,
        "fields": [
          {
            "name": "_id",
            "description": null,
            "args": [],
            "type": {
              "kind": "SCALAR",
              "name": "ID",
              "ofType": null
            },
            "isDeprecated": false,
            "deprecationReason": null
          },
          {
            "name": "operatorId",
            "description": null,
            "args": [],
            "type": {
              "kind": "SCALAR",
              "name": "ID",
              "ofType": null
            },
            "isDeprecated": false,
            "deprecationReason": null
          },
          {
            "name": "apnName",
            "description": null,
            "args": [],
            "type": {
              "kind": "SCALAR",
              "name": "String",
              "ofType": null
            },
            "isDeprecated": false,
            "deprecationReason": null
          },
          {
            "name": "apn",
            "description": null,
            "args": [],
            "type": {
              "kind": "SCALAR",
              "name": "String",
              "ofType": null
            },
            "isDeprecated": false,
            "deprecationReason": null
          },
          {
            "name": "proxy",
            "description": null,
            "args": [],
            "type": {
              "kind": "SCALAR",
              "name": "String",
              "ofType": null
            },
            "isDeprecated": false,
            "deprecationReason": null
          },
          {
            "name": "port",
            "description": null,
            "args": [],
            "type": {
              "kind": "SCALAR",
              "name": "String",
              "ofType": null
            },
            "isDeprecated": false,
            "deprecationReason": null
          },
          {
            "name": "userName",
            "description": null,
            "args": [],
            "type": {
              "kind": "SCALAR",
              "name": "String",
              "ofType": null
            },
            "isDeprecated": false,
            "deprecationReason": null
          },
          {
            "name": "password",
            "description": null,
            "args": [],
            "type": {
              "kind": "SCALAR",
              "name": "String",
              "ofType": null
            },
            "isDeprecated": false,
            "deprecationReason": null
          },
          {
            "name": "server",
            "description": null,
            "args": [],
            "type": {
              "kind": "SCALAR",
              "name": "String",
              "ofType": null
            },
            "isDeprecated": false,
            "deprecationReason": null
          },
          {
            "name": "mmsc",
            "description": null,
            "args": [],
            "type": {
              "kind": "SCALAR",
              "name": "String",
              "ofType": null
            },
            "isDeprecated": false,
            "deprecationReason": null
          },
          {
            "name": "mmsProxy",
            "description": null,
            "args": [],
            "type": {
              "kind": "SCALAR",
              "name": "String",
              "ofType": null
            },
            "isDeprecated": false,
            "deprecationReason": null
          },
          {
            "name": "mmsPort",
            "description": null,
            "args": [],
            "type": {
              "kind": "SCALAR",
              "name": "String",
              "ofType": null
            },
            "isDeprecated": false,
            "deprecationReason": null
          },
          {
            "name": "mcc",
            "description": null,
            "args": [],
            "type": {
              "kind": "SCALAR",
              "name": "String",
              "ofType": null
            },
            "isDeprecated": false,
            "deprecationReason": null
          },
          {
            "name": "mnc",
            "description": null,
            "args": [],
            "type": {
              "kind": "SCALAR",
              "name": "String",
              "ofType": null
            },
            "isDeprecated": false,
            "deprecationReason": null
          },
          {
            "name": "authType",
            "description": null,
            "args": [],
            "type": {
              "kind": "SCALAR",
              "name": "String",
              "ofType": null
            },
            "isDeprecated": false,
            "deprecationReason": null
          },
          {
            "name": "apnType",
            "description": null,
            "args": [],
            "type": {
              "kind": "SCALAR",
              "name": "String",
              "ofType": null
            },
            "isDeprecated": false,
            "deprecationReason": null
          },
          {
            "name": "apnProtocol",
            "description": null,
            "args": [],
            "type": {
              "kind": "SCALAR",
              "name": "String",
              "ofType": null
            },
            "isDeprecated": false,
            "deprecationReason": null
          },
          {
            "name": "apnRoaming",
            "description": null,
            "args": [],
            "type": {
              "kind": "SCALAR",
              "name": "String",
              "ofType": null
            },
            "isDeprecated": false,
            "deprecationReason": null
          },
          {
            "name": "bearer",
            "description": null,
            "args": [],
            "type": {
              "kind": "SCALAR",
              "name": "String",
              "ofType": null
            },
            "isDeprecated": false,
            "deprecationReason": null
          },
          {
            "name": "mvnoType",
            "description": null,
            "args": [],
            "type": {
              "kind": "SCALAR",
              "name": "String",
              "ofType": null
            },
            "isDeprecated": false,
            "deprecationReason": null
          },
          {
            "name": "mvnoValue",
            "description": null,
            "args": [],
            "type": {
              "kind": "SCALAR",
              "name": "String",
              "ofType": null
            },
            "isDeprecated": false,
            "deprecationReason": null
          }
        ],
        "inputFields": null,
        "interfaces": [],
        "enumValues": null,
        "possibleTypes": null
      },
      {
        "kind": "OBJECT",
        "name": "AppConfigRes",
        "description": null,
        "fields": [
          {
            "name": "id",
            "description": null,
            "args": [],
            "type": {
              "kind": "SCALAR",
              "name": "ID",
              "ofType": null
            },
            "isDeprecated": false,
            "deprecationReason": null
          },
          {
            "name": "appConfigRes",
            "description": null,
            "args": [],
            "type": {
              "kind": "SCALAR",
              "name": "JSON",
              "ofType": null
            },
            "isDeprecated": false,
            "deprecationReason": null
          }
        ],
        "inputFields": null,
        "interfaces": [],
        "enumValues": null,
        "possibleTypes": null
      },
      {
        "kind": "SCALAR",
        "name": "JSON",
        "description": null,
        "fields": null,
        "inputFields": null,
        "interfaces": null,
        "enumValues": null,
        "possibleTypes": null
      },
      {
        "kind": "OBJECT",
        "name": "Thread",
        "description": null,
        "fields": [
          {
            "name": "id",
            "description": null,
            "args": [],
            "type": {
              "kind": "SCALAR",
              "name": "ID",
              "ofType": null
            },
            "isDeprecated": false,
            "deprecationReason": null
          },
          {
            "name": "lastSenderId",
            "description": null,
            "args": [],
            "type": {
              "kind": "SCALAR",
              "name": "ID",
              "ofType": null
            },
            "isDeprecated": false,
            "deprecationReason": null
          },
          {
            "name": "message",
            "description": null,
            "args": [],
            "type": {
              "kind": "SCALAR",
              "name": "String",
              "ofType": null
            },
            "isDeprecated": false,
            "deprecationReason": null
          },
          {
            "name": "date",
            "description": null,
            "args": [],
            "type": {
              "kind": "SCALAR",
              "name": "String",
              "ofType": null
            },
            "isDeprecated": false,
            "deprecationReason": null
          },
          {
            "name": "recipientsIds",
            "description": null,
            "args": [],
            "type": {
              "kind": "LIST",
              "name": null,
              "ofType": {
                "kind": "SCALAR",
                "name": "ID",
                "ofType": null
              }
            },
            "isDeprecated": false,
            "deprecationReason": null
          },
          {
            "name": "currentUser",
            "description": null,
            "args": [],
            "type": {
              "kind": "SCALAR",
              "name": "Int",
              "ofType": null
            },
            "isDeprecated": false,
            "deprecationReason": null
          },
          {
            "name": "unreadCount",
            "description": null,
            "args": [],
            "type": {
              "kind": "SCALAR",
              "name": "Int",
              "ofType": null
            },
            "isDeprecated": false,
            "deprecationReason": null
          },
          {
            "name": "recipientsCount",
            "description": null,
            "args": [],
            "type": {
              "kind": "SCALAR",
              "name": "Int",
              "ofType": null
            },
            "isDeprecated": false,
            "deprecationReason": null
          },
          {
            "name": "recipientUser",
            "description": null,
            "args": [],
            "type": {
              "kind": "SCALAR",
              "name": "String",
              "ofType": null
            },
            "isDeprecated": false,
            "deprecationReason": null
          },
          {
            "name": "isGroup",
            "description": null,
            "args": [],
            "type": {
              "kind": "SCALAR",
              "name": "Boolean",
              "ofType": null
            },
            "isDeprecated": false,
            "deprecationReason": null
          },
          {
            "name": "groupName",
            "description": null,
            "args": [],
            "type": {
              "kind": "SCALAR",
              "name": "String",
              "ofType": null
            },
            "isDeprecated": false,
            "deprecationReason": null
          },
          {
            "name": "deletedForUser",
            "description": null,
            "args": [],
            "type": {
              "kind": "LIST",
              "name": null,
              "ofType": {
                "kind": "SCALAR",
                "name": "String",
                "ofType": null
              }
            },
            "isDeprecated": false,
            "deprecationReason": null
          }
        ],
        "inputFields": null,
        "interfaces": [],
        "enumValues": null,
        "possibleTypes": null
      },
      {
        "kind": "OBJECT",
        "name": "ThreadListRes",
        "description": null,
        "fields": [
          {
            "name": "recipientUser",
            "description": null,
            "args": [],
            "type": {
              "kind": "LIST",
              "name": null,
              "ofType": {
                "kind": "OBJECT",
                "name": "UserData",
                "ofType": null
              }
            },
            "isDeprecated": false,
            "deprecationReason": null
          }
        ],
        "inputFields": null,
        "interfaces": [],
        "enumValues": null,
        "possibleTypes": null
      },
      {
        "kind": "OBJECT",
        "name": "Attachment",
        "description": null,
        "fields": [
          {
            "name": "messageId",
            "description": null,
            "args": [],
            "type": {
              "kind": "SCALAR",
              "name": "ID",
              "ofType": null
            },
            "isDeprecated": false,
            "deprecationReason": null
          },
          {
            "name": "attachmentType",
            "description": null,
            "args": [],
            "type": {
              "kind": "SCALAR",
              "name": "String",
              "ofType": null
            },
            "isDeprecated": false,
            "deprecationReason": null
          },
          {
            "name": "url",
            "description": null,
            "args": [],
            "type": {
              "kind": "SCALAR",
              "name": "String",
              "ofType": null
            },
            "isDeprecated": false,
            "deprecationReason": null
          }
        ],
        "inputFields": null,
        "interfaces": [],
        "enumValues": null,
        "possibleTypes": null
      },
      {
        "kind": "OBJECT",
        "name": "Message",
        "description": null,
        "fields": [
          {
            "name": "_id",
            "description": null,
            "args": [],
            "type": {
              "kind": "SCALAR",
              "name": "ID",
              "ofType": null
            },
            "isDeprecated": false,
            "deprecationReason": null
          },
          {
            "name": "threadId",
            "description": null,
            "args": [],
            "type": {
              "kind": "SCALAR",
              "name": "ID",
              "ofType": null
            },
            "isDeprecated": false,
            "deprecationReason": null
          },
          {
            "name": "senderId",
            "description": null,
            "args": [],
            "type": {
              "kind": "SCALAR",
              "name": "ID",
              "ofType": null
            },
            "isDeprecated": false,
            "deprecationReason": null
          },
          {
            "name": "message",
            "description": null,
            "args": [],
            "type": {
              "kind": "SCALAR",
              "name": "String",
              "ofType": null
            },
            "isDeprecated": false,
            "deprecationReason": null
          },
          {
            "name": "dateSend",
            "description": null,
            "args": [],
            "type": {
              "kind": "SCALAR",
              "name": "String",
              "ofType": null
            },
            "isDeprecated": false,
            "deprecationReason": null
          },
          {
            "name": "isAttachment",
            "description": null,
            "args": [],
            "type": {
              "kind": "SCALAR",
              "name": "Boolean",
              "ofType": null
            },
            "isDeprecated": false,
            "deprecationReason": null
          },
          {
            "name": "attachmentId",
            "description": null,
            "args": [],
            "type": {
              "kind": "SCALAR",
              "name": "ID",
              "ofType": null
            },
            "isDeprecated": false,
            "deprecationReason": null
          },
          {
            "name": "url",
            "description": null,
            "args": [],
            "type": {
              "kind": "SCALAR",
              "name": "String",
              "ofType": null
            },
            "isDeprecated": false,
            "deprecationReason": null
          },
          {
            "name": "isDeleted",
            "description": null,
            "args": [],
            "type": {
              "kind": "SCALAR",
              "name": "Boolean",
              "ofType": null
            },
            "isDeprecated": false,
            "deprecationReason": null
          },
          {
            "name": "deletedForUser",
            "description": null,
            "args": [],
            "type": {
              "kind": "LIST",
              "name": null,
              "ofType": {
                "kind": "SCALAR",
                "name": "String",
                "ofType": null
              }
            },
            "isDeprecated": false,
            "deprecationReason": null
          }
        ],
        "inputFields": null,
        "interfaces": [],
        "enumValues": null,
        "possibleTypes": null
      },
      {
        "kind": "OBJECT",
        "name": "GetMessageListRes",
        "description": null,
        "fields": [
          {
            "name": "messages",
            "description": null,
            "args": [],
            "type": {
              "kind": "LIST",
              "name": null,
              "ofType": {
                "kind": "OBJECT",
                "name": "MessageData",
                "ofType": null
              }
            },
            "isDeprecated": false,
            "deprecationReason": null
          }
        ],
        "inputFields": null,
        "interfaces": [],
        "enumValues": null,
        "possibleTypes": null
      },
      {
        "kind": "OBJECT",
        "name": "MessageData",
        "description": null,
        "fields": [
          {
            "name": "id",
            "description": null,
            "args": [],
            "type": {
              "kind": "SCALAR",
              "name": "ID",
              "ofType": null
            },
            "isDeprecated": false,
            "deprecationReason": null
          },
          {
            "name": "threadId",
            "description": null,
            "args": [],
            "type": {
              "kind": "SCALAR",
              "name": "ID",
              "ofType": null
            },
            "isDeprecated": false,
            "deprecationReason": null
          },
          {
            "name": "senderId",
            "description": null,
            "args": [],
            "type": {
              "kind": "SCALAR",
              "name": "ID",
              "ofType": null
            },
            "isDeprecated": false,
            "deprecationReason": null
          },
          {
            "name": "message",
            "description": null,
            "args": [],
            "type": {
              "kind": "SCALAR",
              "name": "String",
              "ofType": null
            },
            "isDeprecated": false,
            "deprecationReason": null
          },
          {
            "name": "dateSent",
            "description": null,
            "args": [],
            "type": {
              "kind": "SCALAR",
              "name": "Date",
              "ofType": null
            },
            "isDeprecated": false,
            "deprecationReason": null
          },
          {
            "name": "userName",
            "description": null,
            "args": [],
            "type": {
              "kind": "SCALAR",
              "name": "String",
              "ofType": null
            },
            "isDeprecated": false,
            "deprecationReason": null
          }
        ],
        "inputFields": null,
        "interfaces": [],
        "enumValues": null,
        "possibleTypes": null
      },
      {
        "kind": "OBJECT",
        "name": "Mutation",
        "description": null,
        "fields": [
          {
            "name": "registerUser",
            "description": null,
            "args": [
              {
                "name": "name",
                "description": null,
                "type": {
                  "kind": "SCALAR",
                  "name": "String",
                  "ofType": null
                },
                "defaultValue": null
              },
              {
                "name": "operatorId",
                "description": null,
                "type": {
                  "kind": "SCALAR",
                  "name": "ID",
                  "ofType": null
                },
                "defaultValue": null
              },
              {
                "name": "msisdn",
                "description": null,
                "type": {
                  "kind": "SCALAR",
                  "name": "String",
                  "ofType": null
                },
                "defaultValue": null
              }
            ],
            "type": {
              "kind": "OBJECT",
              "name": "CreateUser",
              "ofType": null
            },
            "isDeprecated": false,
            "deprecationReason": null
          },
          {
            "name": "createOperator",
            "description": null,
            "args": [
              {
                "name": "name",
                "description": null,
                "type": {
                  "kind": "SCALAR",
                  "name": "String",
                  "ofType": null
                },
                "defaultValue": null
              },
              {
                "name": "operatorId",
                "description": null,
                "type": {
                  "kind": "SCALAR",
                  "name": "ID",
                  "ofType": null
                },
                "defaultValue": null
              }
            ],
            "type": {
              "kind": "OBJECT",
              "name": "Operator",
              "ofType": null
            },
            "isDeprecated": false,
            "deprecationReason": null
          },
          {
            "name": "createAccessPointName",
            "description": null,
            "args": [
              {
                "name": "apnInput",
                "description": null,
                "type": {
                  "kind": "INPUT_OBJECT",
                  "name": "APNInput",
                  "ofType": null
                },
                "defaultValue": null
              }
            ],
            "type": {
              "kind": "OBJECT",
              "name": "apnRes",
              "ofType": null
            },
            "isDeprecated": false,
            "deprecationReason": null
          },
          {
            "name": "createAppConfig",
            "description": null,
            "args": [
              {
                "name": "operatorId",
                "description": null,
                "type": {
                  "kind": "SCALAR",
                  "name": "ID",
                  "ofType": null
                },
                "defaultValue": null
              },
              {
                "name": "appConfig",
                "description": null,
                "type": {
                  "kind": "LIST",
                  "name": null,
                  "ofType": {
                    "kind": "INPUT_OBJECT",
                    "name": "AppConfigInput",
                    "ofType": null
                  }
                },
                "defaultValue": null
              }
            ],
            "type": {
              "kind": "OBJECT",
              "name": "AppConfigRes",
              "ofType": null
            },
            "isDeprecated": false,
            "deprecationReason": null
          },
          {
            "name": "createThread",
            "description": null,
            "args": [
              {
                "name": "threadInput",
                "description": null,
                "type": {
                  "kind": "INPUT_OBJECT",
                  "name": "ThreadInput",
                  "ofType": null
                },
                "defaultValue": null
              }
            ],
            "type": {
              "kind": "OBJECT",
              "name": "Thread",
              "ofType": null
            },
            "isDeprecated": false,
            "deprecationReason": null
          },
          {
            "name": "deleteThread",
            "description": null,
            "args": [
              {
                "name": "deleteThreadInput",
                "description": null,
                "type": {
                  "kind": "INPUT_OBJECT",
                  "name": "DeleteThreadInput",
                  "ofType": null
                },
                "defaultValue": null
              }
            ],
            "type": {
              "kind": "OBJECT",
              "name": "ThreadRes",
              "ofType": null
            },
            "isDeprecated": false,
            "deprecationReason": null
          },
          {
            "name": "createAttachment",
            "description": null,
            "args": [
              {
                "name": "attachmentInput",
                "description": null,
                "type": {
                  "kind": "INPUT_OBJECT",
                  "name": "AttachmentInput",
                  "ofType": null
                },
                "defaultValue": null
              }
            ],
            "type": {
              "kind": "OBJECT",
              "name": "Attachment",
              "ofType": null
            },
            "isDeprecated": false,
            "deprecationReason": null
          },
          {
            "name": "createMessage",
            "description": null,
            "args": [
              {
                "name": "messageInput",
                "description": null,
                "type": {
                  "kind": "INPUT_OBJECT",
                  "name": "MessageInput",
                  "ofType": null
                },
                "defaultValue": null
              }
            ],
            "type": {
              "kind": "OBJECT",
              "name": "Message",
              "ofType": null
            },
            "isDeprecated": false,
            "deprecationReason": null
          },
          {
            "name": "deleteMessages",
            "description": null,
            "args": [
              {
                "name": "deleteMessageInput",
                "description": null,
                "type": {
                  "kind": "INPUT_OBJECT",
                  "name": "DeleteMessageInput",
                  "ofType": null
                },
                "defaultValue": null
              }
            ],
            "type": {
              "kind": "OBJECT",
              "name": "DeleteMessageRes",
              "ofType": null
            },
            "isDeprecated": false,
            "deprecationReason": null
          }
        ],
        "inputFields": null,
        "interfaces": [],
        "enumValues": null,
        "possibleTypes": null
      },
      {
        "kind": "OBJECT",
        "name": "CreateUser",
        "description": null,
        "fields": [
          {
            "name": "userId",
            "description": null,
            "args": [],
            "type": {
              "kind": "SCALAR",
              "name": "ID",
              "ofType": null
            },
            "isDeprecated": false,
            "deprecationReason": null
          },
          {
            "name": "message",
            "description": null,
            "args": [],
            "type": {
              "kind": "SCALAR",
              "name": "String",
              "ofType": null
            },
            "isDeprecated": false,
            "deprecationReason": null
          },
          {
            "name": "token",
            "description": null,
            "args": [],
            "type": {
              "kind": "SCALAR",
              "name": "String",
              "ofType": null
            },
            "isDeprecated": false,
            "deprecationReason": null
          },
          {
            "name": "status",
            "description": null,
            "args": [],
            "type": {
              "kind": "SCALAR",
              "name": "Int",
              "ofType": null
            },
            "isDeprecated": false,
            "deprecationReason": null
          },
          {
            "name": "userData",
            "description": null,
            "args": [],
            "type": {
              "kind": "OBJECT",
              "name": "UserData",
              "ofType": null
            },
            "isDeprecated": false,
            "deprecationReason": null
          },
          {
            "name": "threadId",
            "description": null,
            "args": [],
            "type": {
              "kind": "SCALAR",
              "name": "ID",
              "ofType": null
            },
            "isDeprecated": false,
            "deprecationReason": null
          }
        ],
        "inputFields": null,
        "interfaces": [],
        "enumValues": null,
        "possibleTypes": null
      },
      {
        "kind": "INPUT_OBJECT",
        "name": "APNInput",
        "description": null,
        "fields": null,
        "inputFields": [
          {
            "name": "operatorId",
            "description": null,
            "type": {
              "kind": "SCALAR",
              "name": "ID",
              "ofType": null
            },
            "defaultValue": null
          },
          {
            "name": "apnName",
            "description": null,
            "type": {
              "kind": "SCALAR",
              "name": "String",
              "ofType": null
            },
            "defaultValue": null
          },
          {
            "name": "apn",
            "description": null,
            "type": {
              "kind": "SCALAR",
              "name": "String",
              "ofType": null
            },
            "defaultValue": null
          },
          {
            "name": "proxy",
            "description": null,
            "type": {
              "kind": "SCALAR",
              "name": "String",
              "ofType": null
            },
            "defaultValue": null
          },
          {
            "name": "port",
            "description": null,
            "type": {
              "kind": "SCALAR",
              "name": "String",
              "ofType": null
            },
            "defaultValue": null
          },
          {
            "name": "userName",
            "description": null,
            "type": {
              "kind": "SCALAR",
              "name": "String",
              "ofType": null
            },
            "defaultValue": null
          },
          {
            "name": "password",
            "description": null,
            "type": {
              "kind": "SCALAR",
              "name": "String",
              "ofType": null
            },
            "defaultValue": null
          },
          {
            "name": "server",
            "description": null,
            "type": {
              "kind": "SCALAR",
              "name": "String",
              "ofType": null
            },
            "defaultValue": null
          },
          {
            "name": "mmsc",
            "description": null,
            "type": {
              "kind": "SCALAR",
              "name": "String",
              "ofType": null
            },
            "defaultValue": null
          },
          {
            "name": "mmsProxy",
            "description": null,
            "type": {
              "kind": "SCALAR",
              "name": "String",
              "ofType": null
            },
            "defaultValue": null
          },
          {
            "name": "mmsPort",
            "description": null,
            "type": {
              "kind": "SCALAR",
              "name": "String",
              "ofType": null
            },
            "defaultValue": null
          },
          {
            "name": "mcc",
            "description": null,
            "type": {
              "kind": "SCALAR",
              "name": "String",
              "ofType": null
            },
            "defaultValue": null
          },
          {
            "name": "mnc",
            "description": null,
            "type": {
              "kind": "SCALAR",
              "name": "String",
              "ofType": null
            },
            "defaultValue": null
          },
          {
            "name": "authType",
            "description": null,
            "type": {
              "kind": "SCALAR",
              "name": "String",
              "ofType": null
            },
            "defaultValue": null
          },
          {
            "name": "apnType",
            "description": null,
            "type": {
              "kind": "SCALAR",
              "name": "String",
              "ofType": null
            },
            "defaultValue": null
          },
          {
            "name": "apnProtocol",
            "description": null,
            "type": {
              "kind": "SCALAR",
              "name": "String",
              "ofType": null
            },
            "defaultValue": null
          },
          {
            "name": "apnRoaming",
            "description": null,
            "type": {
              "kind": "SCALAR",
              "name": "String",
              "ofType": null
            },
            "defaultValue": null
          },
          {
            "name": "bearer",
            "description": null,
            "type": {
              "kind": "SCALAR",
              "name": "String",
              "ofType": null
            },
            "defaultValue": null
          },
          {
            "name": "mvnoType",
            "description": null,
            "type": {
              "kind": "SCALAR",
              "name": "String",
              "ofType": null
            },
            "defaultValue": null
          },
          {
            "name": "mvnoValue",
            "description": null,
            "type": {
              "kind": "SCALAR",
              "name": "String",
              "ofType": null
            },
            "defaultValue": null
          }
        ],
        "interfaces": null,
        "enumValues": null,
        "possibleTypes": null
      },
      {
        "kind": "OBJECT",
        "name": "apnRes",
        "description": null,
        "fields": [
          {
            "name": "id",
            "description": null,
            "args": [],
            "type": {
              "kind": "SCALAR",
              "name": "ID",
              "ofType": null
            },
            "isDeprecated": false,
            "deprecationReason": null
          }
        ],
        "inputFields": null,
        "interfaces": [],
        "enumValues": null,
        "possibleTypes": null
      },
      {
        "kind": "INPUT_OBJECT",
        "name": "AppConfigInput",
        "description": null,
        "fields": null,
        "inputFields": [
          {
            "name": "configName",
            "description": null,
            "type": {
              "kind": "SCALAR",
              "name": "String",
              "ofType": null
            },
            "defaultValue": null
          },
          {
            "name": "configValue",
            "description": null,
            "type": {
              "kind": "SCALAR",
              "name": "String",
              "ofType": null
            },
            "defaultValue": null
          },
          {
            "name": "apkLink",
            "description": null,
            "type": {
              "kind": "SCALAR",
              "name": "String",
              "ofType": null
            },
            "defaultValue": null
          }
        ],
        "interfaces": null,
        "enumValues": null,
        "possibleTypes": null
      },
      {
        "kind": "INPUT_OBJECT",
        "name": "ThreadInput",
        "description": null,
        "fields": null,
        "inputFields": [
          {
            "name": "lastSenderId",
            "description": null,
            "type": {
              "kind": "SCALAR",
              "name": "ID",
              "ofType": null
            },
            "defaultValue": null
          },
          {
            "name": "message",
            "description": null,
            "type": {
              "kind": "SCALAR",
              "name": "String",
              "ofType": null
            },
            "defaultValue": null
          },
          {
            "name": "date",
            "description": null,
            "type": {
              "kind": "SCALAR",
              "name": "String",
              "ofType": null
            },
            "defaultValue": null
          },
          {
            "name": "recipientsIds",
            "description": null,
            "type": {
              "kind": "LIST",
              "name": null,
              "ofType": {
                "kind": "SCALAR",
                "name": "ID",
                "ofType": null
              }
            },
            "defaultValue": null
          },
          {
            "name": "currentUser",
            "description": null,
            "type": {
              "kind": "SCALAR",
              "name": "Int",
              "ofType": null
            },
            "defaultValue": null
          },
          {
            "name": "unreadCount",
            "description": null,
            "type": {
              "kind": "SCALAR",
              "name": "Int",
              "ofType": null
            },
            "defaultValue": null
          },
          {
            "name": "recipientsCount",
            "description": null,
            "type": {
              "kind": "SCALAR",
              "name": "Int",
              "ofType": null
            },
            "defaultValue": null
          },
          {
            "name": "recipientUser",
            "description": null,
            "type": {
              "kind": "SCALAR",
              "name": "String",
              "ofType": null
            },
            "defaultValue": null
          },
          {
            "name": "isGroup",
            "description": null,
            "type": {
              "kind": "SCALAR",
              "name": "Boolean",
              "ofType": null
            },
            "defaultValue": null
          },
          {
            "name": "groupName",
            "description": null,
            "type": {
              "kind": "SCALAR",
              "name": "String",
              "ofType": null
            },
            "defaultValue": null
          }
        ],
        "interfaces": null,
        "enumValues": null,
        "possibleTypes": null
      },
      {
        "kind": "INPUT_OBJECT",
        "name": "DeleteThreadInput",
        "description": null,
        "fields": null,
        "inputFields": [
          {
            "name": "threadId",
            "description": null,
            "type": {
              "kind": "LIST",
              "name": null,
              "ofType": {
                "kind": "SCALAR",
                "name": "ID",
                "ofType": null
              }
            },
            "defaultValue": null
          },
          {
            "name": "userId",
            "description": null,
            "type": {
              "kind": "SCALAR",
              "name": "ID",
              "ofType": null
            },
            "defaultValue": null
          }
        ],
        "interfaces": null,
        "enumValues": null,
        "possibleTypes": null
      },
      {
        "kind": "OBJECT",
        "name": "ThreadRes",
        "description": null,
        "fields": [
          {
            "name": "threadDelRes",
            "description": null,
            "args": [],
            "type": {
              "kind": "SCALAR",
              "name": "String",
              "ofType": null
            },
            "isDeprecated": false,
            "deprecationReason": null
          }
        ],
        "inputFields": null,
        "interfaces": [],
        "enumValues": null,
        "possibleTypes": null
      },
      {
        "kind": "INPUT_OBJECT",
        "name": "AttachmentInput",
        "description": null,
        "fields": null,
        "inputFields": [
          {
            "name": "messageId",
            "description": null,
            "type": {
              "kind": "SCALAR",
              "name": "ID",
              "ofType": null
            },
            "defaultValue": null
          },
          {
            "name": "attachmentType",
            "description": null,
            "type": {
              "kind": "SCALAR",
              "name": "String",
              "ofType": null
            },
            "defaultValue": null
          },
          {
            "name": "url",
            "description": null,
            "type": {
              "kind": "SCALAR",
              "name": "String",
              "ofType": null
            },
            "defaultValue": null
          }
        ],
        "interfaces": null,
        "enumValues": null,
        "possibleTypes": null
      },
      {
        "kind": "INPUT_OBJECT",
        "name": "MessageInput",
        "description": null,
        "fields": null,
        "inputFields": [
          {
            "name": "threadId",
            "description": null,
            "type": {
              "kind": "SCALAR",
              "name": "ID",
              "ofType": null
            },
            "defaultValue": null
          },
          {
            "name": "senderId",
            "description": null,
            "type": {
              "kind": "SCALAR",
              "name": "ID",
              "ofType": null
            },
            "defaultValue": null
          },
          {
            "name": "message",
            "description": null,
            "type": {
              "kind": "SCALAR",
              "name": "String",
              "ofType": null
            },
            "defaultValue": null
          },
          {
            "name": "dateSend",
            "description": null,
            "type": {
              "kind": "SCALAR",
              "name": "String",
              "ofType": null
            },
            "defaultValue": null
          },
          {
            "name": "isAttachment",
            "description": null,
            "type": {
              "kind": "SCALAR",
              "name": "Boolean",
              "ofType": null
            },
            "defaultValue": null
          },
          {
            "name": "attachmentType",
            "description": null,
            "type": {
              "kind": "ENUM",
              "name": "AttachmentTypeEnum",
              "ofType": null
            },
            "defaultValue": null
          },
          {
            "name": "attachmentId",
            "description": null,
            "type": {
              "kind": "SCALAR",
              "name": "ID",
              "ofType": null
            },
            "defaultValue": null
          },
          {
            "name": "url",
            "description": null,
            "type": {
              "kind": "SCALAR",
              "name": "String",
              "ofType": null
            },
            "defaultValue": null
          }
        ],
        "interfaces": null,
        "enumValues": null,
        "possibleTypes": null
      },
      {
        "kind": "ENUM",
        "name": "AttachmentTypeEnum",
        "description": null,
        "fields": null,
        "inputFields": null,
        "interfaces": null,
        "enumValues": [
          {
            "name": "text",
            "description": null,
            "isDeprecated": false,
            "deprecationReason": null
          },
          {
            "name": "image",
            "description": null,
            "isDeprecated": false,
            "deprecationReason": null
          },
          {
            "name": "video",
            "description": null,
            "isDeprecated": false,
            "deprecationReason": null
          }
        ],
        "possibleTypes": null
      },
      {
        "kind": "INPUT_OBJECT",
        "name": "DeleteMessageInput",
        "description": null,
        "fields": null,
        "inputFields": [
          {
            "name": "threadId",
            "description": null,
            "type": {
              "kind": "SCALAR",
              "name": "ID",
              "ofType": null
            },
            "defaultValue": null
          },
          {
            "name": "userId",
            "description": null,
            "type": {
              "kind": "SCALAR",
              "name": "ID",
              "ofType": null
            },
            "defaultValue": null
          },
          {
            "name": "messageId",
            "description": null,
            "type": {
              "kind": "LIST",
              "name": null,
              "ofType": {
                "kind": "SCALAR",
                "name": "ID",
                "ofType": null
              }
            },
            "defaultValue": null
          },
          {
            "name": "attachmentId",
            "description": null,
            "type": {
              "kind": "SCALAR",
              "name": "ID",
              "ofType": null
            },
            "defaultValue": null
          }
        ],
        "interfaces": null,
        "enumValues": null,
        "possibleTypes": null
      },
      {
        "kind": "OBJECT",
        "name": "DeleteMessageRes",
        "description": null,
        "fields": [
          {
            "name": "messageId",
            "description": null,
            "args": [],
            "type": {
              "kind": "SCALAR",
              "name": "ID",
              "ofType": null
            },
            "isDeprecated": false,
            "deprecationReason": null
          },
          {
            "name": "messageRes",
            "description": null,
            "args": [],
            "type": {
              "kind": "SCALAR",
              "name": "String",
              "ofType": null
            },
            "isDeprecated": false,
            "deprecationReason": null
          }
        ],
        "inputFields": null,
        "interfaces": [],
        "enumValues": null,
        "possibleTypes": null
      },
      {
        "kind": "OBJECT",
        "name": "__Schema",
        "description": "A GraphQL Schema defines the capabilities of a GraphQL server. It exposes all available types and directives on the server, as well as the entry points for query, mutation, and subscription operations.",
        "fields": [
          {
            "name": "types",
            "description": "A list of all types supported by this server.",
            "args": [],
            "type": {
              "kind": "NON_NULL",
              "name": null,
              "ofType": {
                "kind": "LIST",
                "name": null,
                "ofType": {
                  "kind": "NON_NULL",
                  "name": null,
                  "ofType": {
                    "kind": "OBJECT",
                    "name": "__Type",
                    "ofType": null
                  }
                }
              }
            },
            "isDeprecated": false,
            "deprecationReason": null
          },
          {
            "name": "queryType",
            "description": "The type that query operations will be rooted at.",
            "args": [],
            "type": {
              "kind": "NON_NULL",
              "name": null,
              "ofType": {
                "kind": "OBJECT",
                "name": "__Type",
                "ofType": null
              }
            },
            "isDeprecated": false,
            "deprecationReason": null
          },
          {
            "name": "mutationType",
            "description": "If this server supports mutation, the type that mutation operations will be rooted at.",
            "args": [],
            "type": {
              "kind": "OBJECT",
              "name": "__Type",
              "ofType": null
            },
            "isDeprecated": false,
            "deprecationReason": null
          },
          {
            "name": "subscriptionType",
            "description": "If this server support subscription, the type that subscription operations will be rooted at.",
            "args": [],
            "type": {
              "kind": "OBJECT",
              "name": "__Type",
              "ofType": null
            },
            "isDeprecated": false,
            "deprecationReason": null
          },
          {
            "name": "directives",
            "description": "A list of all directives supported by this server.",
            "args": [],
            "type": {
              "kind": "NON_NULL",
              "name": null,
              "ofType": {
                "kind": "LIST",
                "name": null,
                "ofType": {
                  "kind": "NON_NULL",
                  "name": null,
                  "ofType": {
                    "kind": "OBJECT",
                    "name": "__Directive",
                    "ofType": null
                  }
                }
              }
            },
            "isDeprecated": false,
            "deprecationReason": null
          }
        ],
        "inputFields": null,
        "interfaces": [],
        "enumValues": null,
        "possibleTypes": null
      },
      {
        "kind": "OBJECT",
        "name": "__Type",
        "description": "The fundamental unit of any GraphQL Schema is the type. There are many kinds of types in GraphQL as represented by the `__TypeKind` enum.\n\nDepending on the kind of a type, certain fields describe information about that type. Scalar types provide no information beyond a name and description, while Enum types provide their values. Object and Interface types provide the fields they describe. Abstract types, Union and Interface, provide the Object types possible at runtime. List and NonNull types compose other types.",
        "fields": [
          {
            "name": "kind",
            "description": null,
            "args": [],
            "type": {
              "kind": "NON_NULL",
              "name": null,
              "ofType": {
                "kind": "ENUM",
                "name": "__TypeKind",
                "ofType": null
              }
            },
            "isDeprecated": false,
            "deprecationReason": null
          },
          {
            "name": "name",
            "description": null,
            "args": [],
            "type": {
              "kind": "SCALAR",
              "name": "String",
              "ofType": null
            },
            "isDeprecated": false,
            "deprecationReason": null
          },
          {
            "name": "description",
            "description": null,
            "args": [],
            "type": {
              "kind": "SCALAR",
              "name": "String",
              "ofType": null
            },
            "isDeprecated": false,
            "deprecationReason": null
          },
          {
            "name": "fields",
            "description": null,
            "args": [
              {
                "name": "includeDeprecated",
                "description": null,
                "type": {
                  "kind": "SCALAR",
                  "name": "Boolean",
                  "ofType": null
                },
                "defaultValue": "false"
              }
            ],
            "type": {
              "kind": "LIST",
              "name": null,
              "ofType": {
                "kind": "NON_NULL",
                "name": null,
                "ofType": {
                  "kind": "OBJECT",
                  "name": "__Field",
                  "ofType": null
                }
              }
            },
            "isDeprecated": false,
            "deprecationReason": null
          },
          {
            "name": "interfaces",
            "description": null,
            "args": [],
            "type": {
              "kind": "LIST",
              "name": null,
              "ofType": {
                "kind": "NON_NULL",
                "name": null,
                "ofType": {
                  "kind": "OBJECT",
                  "name": "__Type",
                  "ofType": null
                }
              }
            },
            "isDeprecated": false,
            "deprecationReason": null
          },
          {
            "name": "possibleTypes",
            "description": null,
            "args": [],
            "type": {
              "kind": "LIST",
              "name": null,
              "ofType": {
                "kind": "NON_NULL",
                "name": null,
                "ofType": {
                  "kind": "OBJECT",
                  "name": "__Type",
                  "ofType": null
                }
              }
            },
            "isDeprecated": false,
            "deprecationReason": null
          },
          {
            "name": "enumValues",
            "description": null,
            "args": [
              {
                "name": "includeDeprecated",
                "description": null,
                "type": {
                  "kind": "SCALAR",
                  "name": "Boolean",
                  "ofType": null
                },
                "defaultValue": "false"
              }
            ],
            "type": {
              "kind": "LIST",
              "name": null,
              "ofType": {
                "kind": "NON_NULL",
                "name": null,
                "ofType": {
                  "kind": "OBJECT",
                  "name": "__EnumValue",
                  "ofType": null
                }
              }
            },
            "isDeprecated": false,
            "deprecationReason": null
          },
          {
            "name": "inputFields",
            "description": null,
            "args": [],
            "type": {
              "kind": "LIST",
              "name": null,
              "ofType": {
                "kind": "NON_NULL",
                "name": null,
                "ofType": {
                  "kind": "OBJECT",
                  "name": "__InputValue",
                  "ofType": null
                }
              }
            },
            "isDeprecated": false,
            "deprecationReason": null
          },
          {
            "name": "ofType",
            "description": null,
            "args": [],
            "type": {
              "kind": "OBJECT",
              "name": "__Type",
              "ofType": null
            },
            "isDeprecated": false,
            "deprecationReason": null
          }
        ],
        "inputFields": null,
        "interfaces": [],
        "enumValues": null,
        "possibleTypes": null
      },
      {
        "kind": "ENUM",
        "name": "__TypeKind",
        "description": "An enum describing what kind of type a given `__Type` is.",
        "fields": null,
        "inputFields": null,
        "interfaces": null,
        "enumValues": [
          {
            "name": "SCALAR",
            "description": "Indicates this type is a scalar.",
            "isDeprecated": false,
            "deprecationReason": null
          },
          {
            "name": "OBJECT",
            "description": "Indicates this type is an object. `fields` and `interfaces` are valid fields.",
            "isDeprecated": false,
            "deprecationReason": null
          },
          {
            "name": "INTERFACE",
            "description": "Indicates this type is an interface. `fields` and `possibleTypes` are valid fields.",
            "isDeprecated": false,
            "deprecationReason": null
          },
          {
            "name": "UNION",
            "description": "Indicates this type is a union. `possibleTypes` is a valid field.",
            "isDeprecated": false,
            "deprecationReason": null
          },
          {
            "name": "ENUM",
            "description": "Indicates this type is an enum. `enumValues` is a valid field.",
            "isDeprecated": false,
            "deprecationReason": null
          },
          {
            "name": "INPUT_OBJECT",
            "description": "Indicates this type is an input object. `inputFields` is a valid field.",
            "isDeprecated": false,
            "deprecationReason": null
          },
          {
            "name": "LIST",
            "description": "Indicates this type is a list. `ofType` is a valid field.",
            "isDeprecated": false,
            "deprecationReason": null
          },
          {
            "name": "NON_NULL",
            "description": "Indicates this type is a non-null. `ofType` is a valid field.",
            "isDeprecated": false,
            "deprecationReason": null
          }
        ],
        "possibleTypes": null
      },
      {
        "kind": "OBJECT",
        "name": "__Field",
        "description": "Object and Interface types are described by a list of Fields, each of which has a name, potentially a list of arguments, and a return type.",
        "fields": [
          {
            "name": "name",
            "description": null,
            "args": [],
            "type": {
              "kind": "NON_NULL",
              "name": null,
              "ofType": {
                "kind": "SCALAR",
                "name": "String",
                "ofType": null
              }
            },
            "isDeprecated": false,
            "deprecationReason": null
          },
          {
            "name": "description",
            "description": null,
            "args": [],
            "type": {
              "kind": "SCALAR",
              "name": "String",
              "ofType": null
            },
            "isDeprecated": false,
            "deprecationReason": null
          },
          {
            "name": "args",
            "description": null,
            "args": [],
            "type": {
              "kind": "NON_NULL",
              "name": null,
              "ofType": {
                "kind": "LIST",
                "name": null,
                "ofType": {
                  "kind": "NON_NULL",
                  "name": null,
                  "ofType": {
                    "kind": "OBJECT",
                    "name": "__InputValue",
                    "ofType": null
                  }
                }
              }
            },
            "isDeprecated": false,
            "deprecationReason": null
          },
          {
            "name": "type",
            "description": null,
            "args": [],
            "type": {
              "kind": "NON_NULL",
              "name": null,
              "ofType": {
                "kind": "OBJECT",
                "name": "__Type",
                "ofType": null
              }
            },
            "isDeprecated": false,
            "deprecationReason": null
          },
          {
            "name": "isDeprecated",
            "description": null,
            "args": [],
            "type": {
              "kind": "NON_NULL",
              "name": null,
              "ofType": {
                "kind": "SCALAR",
                "name": "Boolean",
                "ofType": null
              }
            },
            "isDeprecated": false,
            "deprecationReason": null
          },
          {
            "name": "deprecationReason",
            "description": null,
            "args": [],
            "type": {
              "kind": "SCALAR",
              "name": "String",
              "ofType": null
            },
            "isDeprecated": false,
            "deprecationReason": null
          }
        ],
        "inputFields": null,
        "interfaces": [],
        "enumValues": null,
        "possibleTypes": null
      },
      {
        "kind": "OBJECT",
        "name": "__InputValue",
        "description": "Arguments provided to Fields or Directives and the input fields of an InputObject are represented as Input Values which describe their type and optionally a default value.",
        "fields": [
          {
            "name": "name",
            "description": null,
            "args": [],
            "type": {
              "kind": "NON_NULL",
              "name": null,
              "ofType": {
                "kind": "SCALAR",
                "name": "String",
                "ofType": null
              }
            },
            "isDeprecated": false,
            "deprecationReason": null
          },
          {
            "name": "description",
            "description": null,
            "args": [],
            "type": {
              "kind": "SCALAR",
              "name": "String",
              "ofType": null
            },
            "isDeprecated": false,
            "deprecationReason": null
          },
          {
            "name": "type",
            "description": null,
            "args": [],
            "type": {
              "kind": "NON_NULL",
              "name": null,
              "ofType": {
                "kind": "OBJECT",
                "name": "__Type",
                "ofType": null
              }
            },
            "isDeprecated": false,
            "deprecationReason": null
          },
          {
            "name": "defaultValue",
            "description": "A GraphQL-formatted string representing the default value for this input value.",
            "args": [],
            "type": {
              "kind": "SCALAR",
              "name": "String",
              "ofType": null
            },
            "isDeprecated": false,
            "deprecationReason": null
          }
        ],
        "inputFields": null,
        "interfaces": [],
        "enumValues": null,
        "possibleTypes": null
      },
      {
        "kind": "OBJECT",
        "name": "__EnumValue",
        "description": "One possible value for a given Enum. Enum values are unique values, not a placeholder for a string or numeric value. However an Enum value is returned in a JSON response as a string.",
        "fields": [
          {
            "name": "name",
            "description": null,
            "args": [],
            "type": {
              "kind": "NON_NULL",
              "name": null,
              "ofType": {
                "kind": "SCALAR",
                "name": "String",
                "ofType": null
              }
            },
            "isDeprecated": false,
            "deprecationReason": null
          },
          {
            "name": "description",
            "description": null,
            "args": [],
            "type": {
              "kind": "SCALAR",
              "name": "String",
              "ofType": null
            },
            "isDeprecated": false,
            "deprecationReason": null
          },
          {
            "name": "isDeprecated",
            "description": null,
            "args": [],
            "type": {
              "kind": "NON_NULL",
              "name": null,
              "ofType": {
                "kind": "SCALAR",
                "name": "Boolean",
                "ofType": null
              }
            },
            "isDeprecated": false,
            "deprecationReason": null
          },
          {
            "name": "deprecationReason",
            "description": null,
            "args": [],
            "type": {
              "kind": "SCALAR",
              "name": "String",
              "ofType": null
            },
            "isDeprecated": false,
            "deprecationReason": null
          }
        ],
        "inputFields": null,
        "interfaces": [],
        "enumValues": null,
        "possibleTypes": null
      },
      {
        "kind": "OBJECT",
        "name": "__Directive",
        "description": "A Directive provides a way to describe alternate runtime execution and type validation behavior in a GraphQL document.\n\nIn some cases, you need to provide options to alter GraphQL's execution behavior in ways field arguments will not suffice, such as conditionally including or skipping a field. Directives provide this by describing additional information to the executor.",
        "fields": [
          {
            "name": "name",
            "description": null,
            "args": [],
            "type": {
              "kind": "NON_NULL",
              "name": null,
              "ofType": {
                "kind": "SCALAR",
                "name": "String",
                "ofType": null
              }
            },
            "isDeprecated": false,
            "deprecationReason": null
          },
          {
            "name": "description",
            "description": null,
            "args": [],
            "type": {
              "kind": "SCALAR",
              "name": "String",
              "ofType": null
            },
            "isDeprecated": false,
            "deprecationReason": null
          },
          {
            "name": "locations",
            "description": null,
            "args": [],
            "type": {
              "kind": "NON_NULL",
              "name": null,
              "ofType": {
                "kind": "LIST",
                "name": null,
                "ofType": {
                  "kind": "NON_NULL",
                  "name": null,
                  "ofType": {
                    "kind": "ENUM",
                    "name": "__DirectiveLocation",
                    "ofType": null
                  }
                }
              }
            },
            "isDeprecated": false,
            "deprecationReason": null
          },
          {
            "name": "args",
            "description": null,
            "args": [],
            "type": {
              "kind": "NON_NULL",
              "name": null,
              "ofType": {
                "kind": "LIST",
                "name": null,
                "ofType": {
                  "kind": "NON_NULL",
                  "name": null,
                  "ofType": {
                    "kind": "OBJECT",
                    "name": "__InputValue",
                    "ofType": null
                  }
                }
              }
            },
            "isDeprecated": false,
            "deprecationReason": null
          }
        ],
        "inputFields": null,
        "interfaces": [],
        "enumValues": null,
        "possibleTypes": null
      },
      {
        "kind": "ENUM",
        "name": "__DirectiveLocation",
        "description": "A Directive can be adjacent to many parts of the GraphQL language, a __DirectiveLocation describes one such possible adjacencies.",
        "fields": null,
        "inputFields": null,
        "interfaces": null,
        "enumValues": [
          {
            "name": "QUERY",
            "description": "Location adjacent to a query operation.",
            "isDeprecated": false,
            "deprecationReason": null
          },
          {
            "name": "MUTATION",
            "description": "Location adjacent to a mutation operation.",
            "isDeprecated": false,
            "deprecationReason": null
          },
          {
            "name": "SUBSCRIPTION",
            "description": "Location adjacent to a subscription operation.",
            "isDeprecated": false,
            "deprecationReason": null
          },
          {
            "name": "FIELD",
            "description": "Location adjacent to a field.",
            "isDeprecated": false,
            "deprecationReason": null
          },
          {
            "name": "FRAGMENT_DEFINITION",
            "description": "Location adjacent to a fragment definition.",
            "isDeprecated": false,
            "deprecationReason": null
          },
          {
            "name": "FRAGMENT_SPREAD",
            "description": "Location adjacent to a fragment spread.",
            "isDeprecated": false,
            "deprecationReason": null
          },
          {
            "name": "INLINE_FRAGMENT",
            "description": "Location adjacent to an inline fragment.",
            "isDeprecated": false,
            "deprecationReason": null
          },
          {
            "name": "VARIABLE_DEFINITION",
            "description": "Location adjacent to a variable definition.",
            "isDeprecated": false,
            "deprecationReason": null
          },
          {
            "name": "SCHEMA",
            "description": "Location adjacent to a schema definition.",
            "isDeprecated": false,
            "deprecationReason": null
          },
          {
            "name": "SCALAR",
            "description": "Location adjacent to a scalar definition.",
            "isDeprecated": false,
            "deprecationReason": null
          },
          {
            "name": "OBJECT",
            "description": "Location adjacent to an object type definition.",
            "isDeprecated": false,
            "deprecationReason": null
          },
          {
            "name": "FIELD_DEFINITION",
            "description": "Location adjacent to a field definition.",
            "isDeprecated": false,
            "deprecationReason": null
          },
          {
            "name": "ARGUMENT_DEFINITION",
            "description": "Location adjacent to an argument definition.",
            "isDeprecated": false,
            "deprecationReason": null
          },
          {
            "name": "INTERFACE",
            "description": "Location adjacent to an interface definition.",
            "isDeprecated": false,
            "deprecationReason": null
          },
          {
            "name": "UNION",
            "description": "Location adjacent to a union definition.",
            "isDeprecated": false,
            "deprecationReason": null
          },
          {
            "name": "ENUM",
            "description": "Location adjacent to an enum definition.",
            "isDeprecated": false,
            "deprecationReason": null
          },
          {
            "name": "ENUM_VALUE",
            "description": "Location adjacent to an enum value definition.",
            "isDeprecated": false,
            "deprecationReason": null
          },
          {
            "name": "INPUT_OBJECT",
            "description": "Location adjacent to an input object type definition.",
            "isDeprecated": false,
            "deprecationReason": null
          },
          {
            "name": "INPUT_FIELD_DEFINITION",
            "description": "Location adjacent to an input object field definition.",
            "isDeprecated": false,
            "deprecationReason": null
          }
        ],
        "possibleTypes": null
      },
      {
        "kind": "OBJECT",
        "name": "ConfigsValue",
        "description": null,
        "fields": [
          {
            "name": "configName",
            "description": null,
            "args": [],
            "type": {
              "kind": "SCALAR",
              "name": "String",
              "ofType": null
            },
            "isDeprecated": false,
            "deprecationReason": null
          },
          {
            "name": "configValue",
            "description": null,
            "args": [],
            "type": {
              "kind": "SCALAR",
              "name": "String",
              "ofType": null
            },
            "isDeprecated": false,
            "deprecationReason": null
          }
        ],
        "inputFields": null,
        "interfaces": [],
        "enumValues": null,
        "possibleTypes": null
      },
      {
        "kind": "OBJECT",
        "name": "AppConfig",
        "description": null,
        "fields": [
          {
            "name": "_id",
            "description": null,
            "args": [],
            "type": {
              "kind": "SCALAR",
              "name": "ID",
              "ofType": null
            },
            "isDeprecated": false,
            "deprecationReason": null
          },
          {
            "name": "appConfigs",
            "description": null,
            "args": [],
            "type": {
              "kind": "LIST",
              "name": null,
              "ofType": {
                "kind": "OBJECT",
                "name": "ConfigsValue",
                "ofType": null
              }
            },
            "isDeprecated": false,
            "deprecationReason": null
          },
          {
            "name": "operatorId",
            "description": null,
            "args": [],
            "type": {
              "kind": "SCALAR",
              "name": "ID",
              "ofType": null
            },
            "isDeprecated": false,
            "deprecationReason": null
          }
        ],
        "inputFields": null,
        "interfaces": [],
        "enumValues": null,
        "possibleTypes": null
      }
    ],
    "directives": [
      {
        "name": "include",
        "description": "Directs the executor to include this field or fragment only when the `if` argument is true.",
        "locations": [
          "FIELD",
          "FRAGMENT_SPREAD",
          "INLINE_FRAGMENT"
        ],
        "args": [
          {
            "name": "if",
            "description": "Included when true.",
            "type": {
              "kind": "NON_NULL",
              "name": null,
              "ofType": {
                "kind": "SCALAR",
                "name": "Boolean",
                "ofType": null
              }
            },
            "defaultValue": null
          }
        ]
      },
      {
        "name": "skip",
        "description": "Directs the executor to skip this field or fragment when the `if` argument is true.",
        "locations": [
          "FIELD",
          "FRAGMENT_SPREAD",
          "INLINE_FRAGMENT"
        ],
        "args": [
          {
            "name": "if",
            "description": "Skipped when true.",
            "type": {
              "kind": "NON_NULL",
              "name": null,
              "ofType": {
                "kind": "SCALAR",
                "name": "Boolean",
                "ofType": null
              }
            },
            "defaultValue": null
          }
        ]
      },
      {
        "name": "deprecated",
        "description": "Marks an element of a GraphQL schema as no longer supported.",
        "locations": [
          "FIELD_DEFINITION",
          "ARGUMENT_DEFINITION",
          "INPUT_FIELD_DEFINITION",
          "ENUM_VALUE"
        ],
        "args": [
          {
            "name": "reason",
            "description": "Explains why this element was deprecated, usually also including a suggestion for how to access supported similar data. Formatted using the Markdown syntax, as specified by [CommonMark](https://commonmark.org/).",
            "type": {
              "kind": "SCALAR",
              "name": "String",
              "ofType": null
            },
            "defaultValue": "\"No longer supported\""
          }
        ]
      },
      {
        "name": "specifiedBy",
        "description": "Exposes a URL that specifies the behaviour of this scalar.",
        "locations": [
          "SCALAR"
        ],
        "args": [
          {
            "name": "url",
            "description": "The URL that specifies the behaviour of this scalar.",
            "type": {
              "kind": "NON_NULL",
              "name": null,
              "ofType": {
                "kind": "SCALAR",
                "name": "String",
                "ofType": null
              }
            },
            "defaultValue": null
          }
        ]
      }
    ]
  }
}
